contracting/__init__.py
contracting/client.py
contracting/compilation/__init__.py
contracting/compilation/compiler.py
contracting/compilation/linter.py
contracting/compilation/parser.py
contracting/compilation/whitelists.py
contracting/constants.py
contracting/contracts/__init__.py
contracting/contracts/proxythis.py
contracting/contracts/submission.s.py
contracting/contracts/thistest2.py
contracting/execution/__init__.py
contracting/execution/executor.py
contracting/execution/module.py
contracting/execution/runtime.py
contracting/execution/tracer.py
contracting/stdlib/__init__.py
contracting/stdlib/bridge/__init__.py
contracting/stdlib/bridge/access.py
contracting/stdlib/bridge/crypto.py
contracting/stdlib/bridge/decimal.py
contracting/stdlib/bridge/hashing.py
contracting/stdlib/bridge/imports.py
contracting/stdlib/bridge/orm.py
contracting/stdlib/bridge/random.py
contracting/stdlib/bridge/time.py
contracting/stdlib/env.py
contracting/storage/__init__.py
contracting/storage/contract.py
contracting/storage/driver.py
contracting/storage/encoder.py
contracting/storage/hdf5.py
contracting/storage/orm.py
xian_contracting-1.0.2.dist-info/LICENSE
xian_contracting-1.0.2.dist-info/METADATA
xian_contracting-1.0.2.dist-info/WHEEL
xian_contracting-1.0.2.dist-info/RECORD
