Metadata-Version: 2.1
Name: xian-contracting
Version: 1.0.2
Summary: Xian Network Python Contracting Engine
Home-page: https://github.com/xian-network/xian-contracting
License: GPL-3.0-only
Keywords: blockchain,xian,contracting,python
Author: Xian Network
Author-email: info@xian.org
Requires-Python: ==3.11.11
Classifier: Development Status :: 5 - Production/Stable
Classifier: License :: OSI Approved :: GNU General Public License v3 (GPLv3)
Classifier: Programming Language :: Python :: 3
Classifier: Programming Language :: Python :: 3.11
Requires-Dist: astor (==0.8.1)
Requires-Dist: autopep8 (==1.5.7)
Requires-Dist: cachetools
Requires-Dist: h5py
Requires-Dist: iso8601
Requires-Dist: loguru
Requires-Dist: psutil
Requires-Dist: pycodestyle (==2.10.0)
Requires-Dist: pynacl
Project-URL: Repository, https://github.com/xian-network/xian-contracting
